osculari/__init__.py
osculari/datasets/__init__.py
osculari/datasets/dataset_utils.py
osculari/datasets/geometrical_shapes.py
osculari/datasets/gratings.py
osculari/datasets/imutils.py
osculari/models/__init__.py
osculari/models/model_utils.py
osculari/models/pretrained_layers.py
osculari/models/pretrained_models.py
osculari/models/readout.py
osculari/paradigms/__init__.py
osculari/paradigms/adaptive_psychophysics.py
osculari/paradigms/forced_choice.py
osculari/paradigms/paradigm_utils.py
osculari-0.0.4.dist-info/LICENSE
osculari-0.0.4.dist-info/METADATA
osculari-0.0.4.dist-info/WHEEL
osculari-0.0.4.dist-info/top_level.txt
osculari-0.0.4.dist-info/zip-safe
osculari-0.0.4.dist-info/RECORD
