Metadata-Version: 2.1
Name: osculari
Version: 0.0.4
Summary: Open source library to explore artificial neural networks with psychophysical experiments.
Author-email: Arash Akbarinia <akbarinia.arash@gmail.com>
License: MIT License
Project-URL: Homepage, https://github.com/ArashAkbarinia/osculari
Project-URL: Download, https://github.com/ArashAkbarinia/osculari/releases
Project-URL: Bug Tracker, https://github.com/ArashAkbarinia/osculari/issues
Project-URL: Documentation, https://osculari.readthedocs.io/en/latest
Project-URL: Source Code, https://github.com/ArashAkbarinia/osculari
Keywords: deep-neural-networks,psychophysics,cognitive-neuroscience,linear-probing,explainable-ai,interpreting-models
Classifier: Development Status :: 4 - Beta
Classifier: Environment :: Console
Classifier: Environment :: GPU
Classifier: Intended Audience :: Science/Research
Classifier: Programming Language :: Python :: 3 :: Only
Classifier: Programming Language :: Python :: 3.8
Classifier: Programming Language :: Python :: 3.9
Classifier: Programming Language :: Python :: 3.10
Classifier: Programming Language :: Python :: 3.11
Classifier: License :: OSI Approved :: MIT License
Classifier: Operating System :: OS Independent
Classifier: Topic :: Scientific/Engineering :: Artificial Intelligence
Classifier: Topic :: Scientific/Engineering :: Information Analysis
Classifier: Topic :: Software Development :: Libraries
Requires-Python: >=3.8
License-File: LICENSE
Requires-Dist: numpy
Requires-Dist: torch
Requires-Dist: torchvision
Requires-Dist: clip-openai
Requires-Dist: visualpriors
Requires-Dist: opencv-python
